[
  {
    "title": "Live: Artemis II Launch Day Updates",
    "link": "https://www.nasa.gov/blogs/missions/2026/04/01/live-artemis-ii-launch-day-updates/",
    "hn_link": "https://news.ycombinator.com/item?id=47603657",
    "score": 909,
    "comments": 776
  },
  {
    "title": "Bringing Clojure programming to Enterprise (2021)",
    "link": "https://blogit.michelin.io/clojure-programming/",
    "hn_link": "https://news.ycombinator.com/item?id=47611481",
    "score": 14,
    "comments": 1
  },
  {
    "title": "Email obfuscation: What works in 2026?",
    "link": "https://spencermortensen.com/articles/email-obfuscation/",
    "hn_link": "https://news.ycombinator.com/item?id=47609694",
    "score": 99,
    "comments": 23
  },
  {
    "title": "Steam on Linux Use Skyrocketed Above 5% in March",
    "link": "https://www.phoronix.com/news/Steam-On-Linux-Tops-5p",
    "hn_link": "https://news.ycombinator.com/item?id=47609564",
    "score": 330,
    "comments": 134
  },
  {
    "title": "Quantum computing bombshells that are not April Fools",
    "link": "https://scottaaronson.blog/?p=9665",
    "hn_link": "https://news.ycombinator.com/item?id=47608495",
    "score": 154,
    "comments": 51
  }
]