[
  {
    "title": "US Court of Appeals: TOS may be updated by email, use can imply consent [pdf]",
    "link": "https://cdn.ca9.uscourts.gov/datastore/memoranda/2026/03/03/25-403.pdf",
    "hn_link": "https://news.ycombinator.com/item?id=47305461",
    "score": 121,
    "comments": 49
  },
  {
    "title": "Grammarly is using our identities without permission",
    "link": "https://www.theverge.com/ai-artificial-intelligence/890921/grammarly-ai-expert-reviews",
    "hn_link": "https://news.ycombinator.com/item?id=47306157",
    "score": 33,
    "comments": 2
  },
  {
    "title": "Agent Safehouse – macOS-native sandboxing for local agents",
    "link": "https://agent-safehouse.dev/",
    "hn_link": "https://news.ycombinator.com/item?id=47301085",
    "score": 553,
    "comments": 137
  },
  {
    "title": "Show HN: Mcp2cli – One CLI for every API, 96-99% fewer tokens than native MCP",
    "link": "https://github.com/knowsuchagency/mcp2cli",
    "hn_link": "https://news.ycombinator.com/item?id=47305149",
    "score": 46,
    "comments": 24
  },
  {
    "title": "Microscopes can see video on a laserdisc",
    "link": "https://www.youtube.com/watch?v=qZuR-772cks",
    "hn_link": "https://news.ycombinator.com/item?id=47291876",
    "score": 409,
    "comments": 47
  }
]